albatros/__init__.py
albatros/copter.py
albatros/enums.py
albatros/nav/__init__.py
albatros/nav/position.py
albatros/outgoing/commands.py
albatros/outgoing/param_messages.py
albatros/plane.py
albatros/py.typed
albatros/setup_logging.py
albatros/telem/__init__.py
albatros/telem/drivers.py
albatros/telem/message_models.py
albatros/telem/models.py
albatros/telem/receive_loop.py
albatros/telem/uav_data.py
albatros/uav.py
albatros_uav-0.16.0.dist-info/LICENSE
albatros_uav-0.16.0.dist-info/METADATA
albatros_uav-0.16.0.dist-info/WHEEL
albatros_uav-0.16.0.dist-info/RECORD
