Metadata-Version: 2.1
Name: albatros-uav
Version: 0.16.0
Summary: The tool for managing unmanned aerial vehicles missions.
Home-page: https://gitlab.com/albatros-uav/albatros
License: LGPL-3.0-only
Author: Jędrzej Stasik
Author-email: jedrzej.stasik@gmail.com
Requires-Python: >=3.9,<4.0
Classifier: License :: OSI Approved :: GNU Lesser General Public License v3 (LGPLv3)
Classifier: Programming Language :: Python :: 3
Classifier: Programming Language :: Python :: 3.9
Classifier: Programming Language :: Python :: 3.10
Classifier: Programming Language :: Python :: 3.11
Classifier: Programming Language :: Python :: 3.12
Requires-Dist: pydantic (>=2.9.2,<3.0.0)
Requires-Dist: pymavlink (>=2.4.41,<3.0.0)
Requires-Dist: pyserial (>=3.5,<4.0)
Project-URL: Documentation, https://albatros-uav.gitlab.io/albatros/
Project-URL: Repository, https://gitlab.com/albatros-uav/albatros
